gbtred/__init__.py
gbtred/baseline.py
gbtred-1.0.0.dist-info/LICENSE
gbtred-1.0.0.dist-info/METADATA
gbtred-1.0.0.dist-info/WHEEL
gbtred-1.0.0.dist-info/top_level.txt
gbtred-1.0.0.dist-info/RECORD
