Metadata-Version: 2.1
Name: gbtred
Version: 1.0.0
Summary: GBT Data Reduction
Home-page: https://github.com/dnidever/gbtred
Author: David Nidever
Author-email: dnidever@montana.edu
License: MIT
Requires: numpy
Requires: astropy(>=4.0)
Requires: scipy
Requires: dlnpyutils
Requires-Python: >=3.6
License-File: LICENSE
Requires-Dist: astropy
Requires-Dist: scipy
Requires-Dist: extension-helpers
Requires-Dist: photutils
Requires-Dist: sep
Requires-Dist: dlnpyutils
Requires-Dist: scikit-image
Provides-Extra: docs
Requires-Dist: sphinx (==3.0.1) ; extra == 'docs'
Requires-Dist: sphinx-astropy ; extra == 'docs'
Requires-Dist: nbsphinx ; extra == 'docs'
Requires-Dist: nbconvert ; extra == 'docs'
Requires-Dist: nbformat ; extra == 'docs'
Requires-Dist: ipykernel ; extra == 'docs'
Provides-Extra: test
Requires-Dist: pytest ; extra == 'test'
Requires-Dist: pytest-astropy ; extra == 'test'
Requires-Dist: ipython ; extra == 'test'
